{
    "calculations": [],
    "changes": [
        {
            "timestamp": "2025-03-13T20:00:15.808117",
            "description": "Configuration Backup",
            "details": "Created backup: config_backup_20250313_200015_4.json",
            "user": "system"
        },
        {
            "timestamp": "2025-03-13T20:00:15.809302",
            "description": "Configuration Backup",
            "details": "Created backup: config_backup_20250313_200015_5.json",
            "user": "system"
        },
        {
            "timestamp": "2025-03-13T20:00:15.810502",
            "description": "Configuration Backup",
            "details": "Created backup: config_backup_20250313_200015_6.json",
            "user": "system"
        },
        {
            "timestamp": "2025-03-13T20:00:15.811562",
            "description": "Configuration Backup",
            "details": "Created backup: config_backup_20250313_200015_7.json",
            "user": "system"
        },
        {
            "timestamp": "2025-03-13T20:00:15.812718",
            "description": "Configuration Backup",
            "details": "Created backup: config_backup_20250313_200015_8.json",
            "user": "system"
        },
        {
            "timestamp": "2025-03-13T20:00:15.813458",
            "description": "Configuration Backup",
            "details": "Created backup: config_backup_20250313_200015_9.json",
            "user": "system"
        },
        {
            "timestamp": "2025-03-13T20:01:21.731569",
            "description": "Updated configuration",
            "details": "Modified sections: mortgage_config, pmi_rates, closing_costs, county_rates, compliance_text, output_templates",
            "user": "admin"
        },
        {
            "timestamp": "2025-03-13T20:01:21.733179",
            "description": "Configuration Backup",
            "details": "Created backup: config_backup_20250313_200121_0.json",
            "user": "system"
        },
        {
            "timestamp": "2025-03-13T20:01:21.734425",
            "description": "Configuration Backup",
            "details": "Created backup: config_backup_20250313_200121_1.json",
            "user": "system"
        },
        {
            "timestamp": "2025-03-13T20:01:21.735510",
            "description": "Configuration Backup",
            "details": "Created backup: config_backup_20250313_200121_2.json",
            "user": "system"
        },
        {
            "timestamp": "2025-03-13T20:01:21.736527",
            "description": "Configuration Backup",
            "details": "Created backup: config_backup_20250313_200121_3.json",
            "user": "system"
        },
        {
            "timestamp": "2025-03-13T20:01:21.737511",
            "description": "Configuration Backup",
            "details": "Created backup: config_backup_20250313_200121_4.json",
            "user": "system"
        },
        {
            "timestamp": "2025-03-13T20:01:21.738971",
            "description": "Configuration Backup",
            "details": "Created backup: config_backup_20250313_200121_5.json",
            "user": "system"
        },
        {
            "timestamp": "2025-03-13T20:01:21.740215",
            "description": "Configuration Backup",
            "details": "Created backup: config_backup_20250313_200121_6.json",
            "user": "system"
        },
        {
            "timestamp": "2025-03-13T20:01:21.741410",
            "description": "Configuration Backup",
            "details": "Created backup: config_backup_20250313_200121_7.json",
            "user": "system"
        },
        {
            "timestamp": "2025-03-13T20:01:21.742485",
            "description": "Configuration Backup",
            "details": "Created backup: config_backup_20250313_200121_8.json",
            "user": "system"
        },
        {
            "timestamp": "2025-03-13T20:01:21.743495",
            "description": "Configuration Backup",
            "details": "Created backup: config_backup_20250313_200121_9.json",
            "user": "system"
        },
        {
            "timestamp": "2025-03-13T20:02:40.861217",
            "description": "Updated configuration",
            "details": "Modified sections: mortgage_config, pmi_rates, closing_costs, county_rates, compliance_text, output_templates",
            "user": "admin"
        },
        {
            "timestamp": "2025-03-13T20:02:40.862566",
            "description": "Configuration Backup",
            "details": "Created backup: config_backup_20250313_200240_0.json",
            "user": "system"
        },
        {
            "timestamp": "2025-03-13T20:02:40.863711",
            "description": "Configuration Backup",
            "details": "Created backup: config_backup_20250313_200240_1.json",
            "user": "system"
        },
        {
            "timestamp": "2025-03-13T20:02:40.864914",
            "description": "Configuration Backup",
            "details": "Created backup: config_backup_20250313_200240_2.json",
            "user": "system"
        },
        {
            "timestamp": "2025-03-13T20:02:40.866263",
            "description": "Configuration Backup",
            "details": "Created backup: config_backup_20250313_200240_3.json",
            "user": "system"
        },
        {
            "timestamp": "2025-03-13T20:02:40.867544",
            "description": "Configuration Backup",
            "details": "Created backup: config_backup_20250313_200240_4.json",
            "user": "system"
        },
        {
            "timestamp": "2025-03-13T20:02:40.868815",
            "description": "Configuration Backup",
            "details": "Created backup: config_backup_20250313_200240_5.json",
            "user": "system"
        },
        {
            "timestamp": "2025-03-13T20:02:40.870026",
            "description": "Configuration Backup",
            "details": "Created backup: config_backup_20250313_200240_6.json",
            "user": "system"
        },
        {
            "timestamp": "2025-03-13T20:02:40.871313",
            "description": "Configuration Backup",
            "details": "Created backup: config_backup_20250313_200240_7.json",
            "user": "system"
        },
        {
            "timestamp": "2025-03-13T20:02:40.872490",
            "description": "Configuration Backup",
            "details": "Created backup: config_backup_20250313_200240_8.json",
            "user": "system"
        },
        {
            "timestamp": "2025-03-13T20:02:40.873567",
            "description": "Configuration Backup",
            "details": "Created backup: config_backup_20250313_200240_9.json",
            "user": "system"
        },
        {
            "timestamp": "2025-03-13T20:03:17.253023",
            "description": "Updated configuration",
            "details": "Modified sections: mortgage_config, pmi_rates, closing_costs, county_rates, compliance_text, output_templates",
            "user": "admin"
        },
        {
            "timestamp": "2025-03-13T20:03:17.254497",
            "description": "Configuration Backup",
            "details": "Created backup: config_backup_20250313_200317_0.json",
            "user": "system"
        },
        {
            "timestamp": "2025-03-13T20:03:17.255948",
            "description": "Configuration Backup",
            "details": "Created backup: config_backup_20250313_200317_1.json",
            "user": "system"
        },
        {
            "timestamp": "2025-03-13T20:03:17.257217",
            "description": "Configuration Backup",
            "details": "Created backup: config_backup_20250313_200317_2.json",
            "user": "system"
        },
        {
            "timestamp": "2025-03-13T20:03:17.258358",
            "description": "Configuration Backup",
            "details": "Created backup: config_backup_20250313_200317_3.json",
            "user": "system"
        },
        {
            "timestamp": "2025-03-13T20:03:17.259389",
            "description": "Configuration Backup",
            "details": "Created backup: config_backup_20250313_200317_4.json",
            "user": "system"
        },
        {
            "timestamp": "2025-03-13T20:03:17.260737",
            "description": "Configuration Backup",
            "details": "Created backup: config_backup_20250313_200317_5.json",
            "user": "system"
        },
        {
            "timestamp": "2025-03-13T20:03:17.261832",
            "description": "Configuration Backup",
            "details": "Created backup: config_backup_20250313_200317_6.json",
            "user": "system"
        },
        {
            "timestamp": "2025-03-13T20:03:17.262909",
            "description": "Configuration Backup",
            "details": "Created backup: config_backup_20250313_200317_7.json",
            "user": "system"
        },
        {
            "timestamp": "2025-03-13T20:03:17.263962",
            "description": "Configuration Backup",
            "details": "Created backup: config_backup_20250313_200317_8.json",
            "user": "system"
        },
        {
            "timestamp": "2025-03-13T20:03:17.265014",
            "description": "Configuration Backup",
            "details": "Created backup: config_backup_20250313_200317_9.json",
            "user": "system"
        },
        {
            "timestamp": "2025-03-13T20:04:50.776411",
            "description": "Updated configuration",
            "details": "Modified sections: mortgage_config, pmi_rates, closing_costs, county_rates, compliance_text, output_templates",
            "user": "admin"
        },
        {
            "timestamp": "2025-03-13T20:04:50.778062",
            "description": "Configuration Backup",
            "details": "Created backup: config_backup_20250313_200450_0.json",
            "user": "system"
        },
        {
            "timestamp": "2025-03-13T20:04:50.779497",
            "description": "Configuration Backup",
            "details": "Created backup: config_backup_20250313_200450_1.json",
            "user": "system"
        },
        {
            "timestamp": "2025-03-13T20:04:50.780777",
            "description": "Configuration Backup",
            "details": "Created backup: config_backup_20250313_200450_2.json",
            "user": "system"
        },
        {
            "timestamp": "2025-03-13T20:04:50.782002",
            "description": "Configuration Backup",
            "details": "Created backup: config_backup_20250313_200450_3.json",
            "user": "system"
        },
        {
            "timestamp": "2025-03-13T20:04:50.783212",
            "description": "Configuration Backup",
            "details": "Created backup: config_backup_20250313_200450_4.json",
            "user": "system"
        },
        {
            "timestamp": "2025-03-13T20:04:50.784464",
            "description": "Configuration Backup",
            "details": "Created backup: config_backup_20250313_200450_5.json",
            "user": "system"
        },
        {
            "timestamp": "2025-03-13T20:04:50.785829",
            "description": "Configuration Backup",
            "details": "Created backup: config_backup_20250313_200450_6.json",
            "user": "system"
        },
        {
            "timestamp": "2025-03-13T20:04:50.787051",
            "description": "Configuration Backup",
            "details": "Created backup: config_backup_20250313_200450_7.json",
            "user": "system"
        },
        {
            "timestamp": "2025-03-13T20:04:50.788167",
            "description": "Configuration Backup",
            "details": "Created backup: config_backup_20250313_200450_8.json",
            "user": "system"
        },
        {
            "timestamp": "2025-03-13T20:04:50.789261",
            "description": "Configuration Backup",
            "details": "Created backup: config_backup_20250313_200450_9.json",
            "user": "system"
        }
    ]
}